<?xml version="1.0" encoding="UTF-8"?>
<MF0 version="1.1" packageUris="http://schema.mathworks.com/mf0/ci/19700101 http://schema.mathworks.com/mf0/sl_data_duplicateandconsistencycheck/R2022b http://schema.mathworks.com/mf0/sl_modelref_info/R2023b http://schema.mathworks.com/mf0/slexec_mm_sto/R2023a_202208151321 http://schema.mathworks.com/mf0/sltp_mm/R2023a_202209151115">
  <ModelRefInfoRepo.ModelRefInfoRoot type="ModelRefInfoRepo.ModelRefInfoRoot" uuid="69566369-b18d-4b7f-b7fd-af807e815f68">
    <JITEngines>shPuiRgpT9tEh4PfDLqxPoE</JITEngines>
    <calibrationData type="ModelRefInfoRepo.CalibrationData" uuid="0a42c791-da63-46e1-92c8-93aee13aa352">
      <InternalData>[{&quot;Name&quot;:&quot;&quot;,&quot;Profile&quot;:&quot;&quot;},{&quot;Name&quot;:&quot;&quot;,&quot;Profile&quot;:&quot;&quot;},{&quot;Name&quot;:&quot;&quot;,&quot;Profile&quot;:&quot;&quot;},{&quot;Name&quot;:&quot;&quot;,&quot;Profile&quot;:&quot;&quot;},{&quot;Name&quot;:&quot;&quot;,&quot;Profile&quot;:&quot;&quot;},{&quot;Name&quot;:&quot;&quot;,&quot;Profile&quot;:&quot;&quot;},{&quot;Name&quot;:&quot;&quot;,&quot;Profile&quot;:&quot;&quot;},{&quot;Name&quot;:&quot;&quot;,&quot;Profile&quot;:&quot;&quot;},{&quot;Name&quot;:&quot;&quot;,&quot;Profile&quot;:&quot;&quot;},{&quot;Name&quot;:&quot;&quot;,&quot;Profile&quot;:&quot;&quot;},{&quot;Name&quot;:&quot;&quot;,&quot;Profile&quot;:&quot;&quot;},{&quot;Name&quot;:&quot;&quot;,&quot;Profile&quot;:&quot;&quot;},{&quot;Name&quot;:&quot;&quot;,&quot;Profile&quot;:&quot;&quot;},{&quot;Name&quot;:&quot;&quot;,&quot;Profile&quot;:&quot;&quot;},{&quot;Name&quot;:&quot;state&quot;,&quot;Profile&quot;:&quot;&quot;},{&quot;Name&quot;:&quot;LS1_R&quot;,&quot;Profile&quot;:&quot;&quot;},{&quot;Name&quot;:&quot;q01&quot;,&quot;Profile&quot;:&quot;&quot;},{&quot;Name&quot;:&quot;pdo_id&quot;,&quot;Profile&quot;:&quot;&quot;},{&quot;Name&quot;:&quot;q02&quot;,&quot;Profile&quot;:&quot;&quot;},{&quot;Name&quot;:&quot;cfg_id&quot;,&quot;Profile&quot;:&quot;&quot;},{&quot;Name&quot;:&quot;num_motors&quot;,&quot;Profile&quot;:&quot;&quot;},{&quot;Name&quot;:&quot;LS1_L&quot;,&quot;Profile&quot;:&quot;&quot;},{&quot;Name&quot;:&quot;LS2_R&quot;,&quot;Profile&quot;:&quot;&quot;},{&quot;Name&quot;:&quot;LS2_L&quot;,&quot;Profile&quot;:&quot;&quot;},{&quot;Name&quot;:&quot;F1&quot;,&quot;Profile&quot;:&quot;&quot;},{&quot;Name&quot;:&quot;F2&quot;,&quot;Profile&quot;:&quot;&quot;},{&quot;Name&quot;:&quot;max_speed&quot;,&quot;Profile&quot;:&quot;&quot;},{&quot;Name&quot;:&quot;max_accel&quot;,&quot;Profile&quot;:&quot;&quot;},{&quot;Name&quot;:&quot;GR1&quot;,&quot;Profile&quot;:&quot;&quot;},{&quot;Name&quot;:&quot;GR2&quot;,&quot;Profile&quot;:&quot;&quot;},{&quot;Name&quot;:&quot;debug&quot;,&quot;Profile&quot;:&quot;&quot;}]</InternalData>
      <ModelName>controller</ModelName>
    </calibrationData>
    <childModelRefInfo type="ModelRefInfoRepo.ChildModelRefInfo" uuid="8288d25e-e860-41e0-8c61-57092b09d403">
      <modelName>controller</modelName>
      <modelPath>controller</modelPath>
    </childModelRefInfo>
    <compiledTFinal>1000.0</compiledTFinal>
    <dataSourceInfo type="ModelRefInfoRepo.DataSourceInfo" uuid="cad6c187-9720-4d8b-9295-34a4d4bf2e34">
      <dataSources type="ModelRefInfoRepo.SourceInfo" uuid="be0e338d-dcc3-418d-acbb-11cabc09e3e7">
        <includeAllSections>true</includeAllSections>
        <sourceName>base workspace</sourceName>
        <type>BaseWorkspace</type>
      </dataSources>
      <modelName>controller</modelName>
    </dataSourceInfo>
    <dataTransferInfos>AAFJTQAAAAAOAAAAOAAAAAYAAAAIAAAAAgAAAAAAAAAFAAAACAAAAAAAAAABAAAAAQAAAAAAAAAFAAQAAQAAAAEAAAAAAAAA</dataTransferInfos>
    <defaultsCMapping>{&quot;Inports&quot;:&quot;{\&quot;Name\&quot;:\&quot;Default\&quot;,\&quot;Checksum\&quot;:\&quot;Default\&quot;,\&quot;PerInstancePropertiesChecksum\&quot;:\&quot;\&quot;,\&quot;MemorySectionName\&quot;:\&quot;None\&quot;,\&quot;MemorySectionChecksum\&quot;:\&quot;None\&quot;}&quot;,&quot;Outports&quot;:&quot;{\&quot;Name\&quot;:\&quot;Default\&quot;,\&quot;Checksum\&quot;:\&quot;Default\&quot;,\&quot;PerInstancePropertiesChecksum\&quot;:\&quot;\&quot;,\&quot;MemorySectionName\&quot;:\&quot;None\&quot;,\&quot;MemorySectionChecksum\&quot;:\&quot;None\&quot;}&quot;,&quot;ParameterArguments&quot;:&quot;{\&quot;Name\&quot;:\&quot;Default\&quot;,\&quot;Checksum\&quot;:\&quot;Default\&quot;,\&quot;PerInstancePropertiesChecksum\&quot;:\&quot;\&quot;,\&quot;MemorySectionName\&quot;:\&quot;None\&quot;,\&quot;MemorySectionChecksum\&quot;:\&quot;None\&quot;}&quot;,&quot;LocalParameters&quot;:&quot;{\&quot;Name\&quot;:\&quot;Default\&quot;,\&quot;Checksum\&quot;:\&quot;Default\&quot;,\&quot;PerInstancePropertiesChecksum\&quot;:\&quot;\&quot;,\&quot;MemorySectionName\&quot;:\&quot;None\&quot;,\&quot;MemorySectionChecksum\&quot;:\&quot;None\&quot;}&quot;,&quot;GlobalParameters&quot;:&quot;{\&quot;Name\&quot;:\&quot;Default\&quot;,\&quot;Checksum\&quot;:\&quot;Default\&quot;,\&quot;PerInstancePropertiesChecksum\&quot;:\&quot;\&quot;,\&quot;MemorySectionName\&quot;:\&quot;None\&quot;,\&quot;MemorySectionChecksum\&quot;:\&quot;None\&quot;}&quot;,&quot;InternalData&quot;:&quot;{\&quot;Name\&quot;:\&quot;Default\&quot;,\&quot;Checksum\&quot;:\&quot;Default\&quot;,\&quot;PerInstancePropertiesChecksum\&quot;:\&quot;\&quot;,\&quot;MemorySectionName\&quot;:\&quot;None\&quot;,\&quot;MemorySectionChecksum\&quot;:\&quot;None\&quot;}&quot;,&quot;SharedLocalDataStores&quot;:&quot;{\&quot;Name\&quot;:\&quot;Default\&quot;,\&quot;Checksum\&quot;:\&quot;Default\&quot;,\&quot;PerInstancePropertiesChecksum\&quot;:\&quot;\&quot;,\&quot;MemorySectionName\&quot;:\&quot;None\&quot;,\&quot;MemorySectionChecksum\&quot;:\&quot;None\&quot;}&quot;,&quot;GlobalDataStores&quot;:&quot;{\&quot;Name\&quot;:\&quot;Default\&quot;,\&quot;Checksum\&quot;:\&quot;Default\&quot;,\&quot;PerInstancePropertiesChecksum\&quot;:\&quot;\&quot;,\&quot;MemorySectionName\&quot;:\&quot;None\&quot;,\&quot;MemorySectionChecksum\&quot;:\&quot;None\&quot;}&quot;,&quot;Constants&quot;:&quot;{\&quot;Name\&quot;:\&quot;Default\&quot;,\&quot;Checksum\&quot;:\&quot;Default\&quot;,\&quot;PerInstancePropertiesChecksum\&quot;:\&quot;\&quot;,\&quot;MemorySectionName\&quot;:\&quot;None\&quot;,\&quot;MemorySectionChecksum\&quot;:\&quot;None\&quot;}&quot;,&quot;DataTransfers&quot;:&quot;{\&quot;Name\&quot;:\&quot;Default\&quot;,\&quot;Checksum\&quot;:\&quot;Default\&quot;,\&quot;PerInstancePropertiesChecksum\&quot;:\&quot;\&quot;,\&quot;MemorySectionName\&quot;:\&quot;None\&quot;,\&quot;MemorySectionChecksum\&quot;:\&quot;None\&quot;}&quot;,&quot;ModelData&quot;:&quot;{\&quot;Name\&quot;:\&quot;Default\&quot;,\&quot;Checksum\&quot;:\&quot;Default\&quot;,\&quot;PerInstancePropertiesChecksum\&quot;:\&quot;\&quot;,\&quot;MemorySectionName\&quot;:\&quot;None\&quot;,\&quot;MemorySectionChecksum\&quot;:\&quot;None\&quot;}&quot;,&quot;InitializeTerminate&quot;:&quot;{\&quot;Name\&quot;:\&quot;Default\&quot;,\&quot;Checksum\&quot;:\&quot;Default\&quot;,\&quot;PerInstancePropertiesChecksum\&quot;:\&quot;\&quot;,\&quot;MemorySectionName\&quot;:\&quot;None\&quot;,\&quot;MemorySectionChecksum\&quot;:\&quot;None\&quot;}&quot;,&quot;Execution&quot;:&quot;{\&quot;Name\&quot;:\&quot;Default\&quot;,\&quot;Checksum\&quot;:\&quot;Default\&quot;,\&quot;PerInstancePropertiesChecksum\&quot;:\&quot;\&quot;,\&quot;MemorySectionName\&quot;:\&quot;None\&quot;,\&quot;MemorySectionChecksum\&quot;:\&quot;None\&quot;}&quot;,&quot;SharedUtility&quot;:&quot;{\&quot;Name\&quot;:\&quot;Default\&quot;,\&quot;Checksum\&quot;:\&quot;Default\&quot;,\&quot;PerInstancePropertiesChecksum\&quot;:\&quot;\&quot;,\&quot;MemorySectionName\&quot;:\&quot;None\&quot;,\&quot;MemorySectionChecksum\&quot;:\&quot;None\&quot;}&quot;}</defaultsCMapping>
    <fastestNoncontSigFeedingDerivPorts>-1.0</fastestNoncontSigFeedingDerivPorts>
    <fundamentalSampleTimePeriod>.001</fundamentalSampleTimePeriod>
    <hasBlockWithPeriodicDiscreteSampleTime>true</hasBlockWithPeriodicDiscreteSampleTime>
    <hasBwsAccessed>true</hasBwsAccessed>
    <hasBwsAccessedByAnyModel>true</hasBwsAccessedByAnyModel>
    <hasNonVirtualConstantTs>true</hasNonVirtualConstantTs>
    <isBdInSimModeForSimCodegenVariants>false</isBdInSimModeForSimCodegenVariants>
    <loggingSaveFormat>2</loggingSaveFormat>
    <maxFreqHz>-1.0</maxFreqHz>
    <numDStateRecs>7</numDStateRecs>
    <numDataInputPorts>0</numDataInputPorts>
    <numLoggableDStateRecs>7</numLoggableDStateRecs>
    <numLoggableJacobianDStates>14</numLoggableJacobianDStates>
    <runtimeNonFcnCallRateInfos type="ModelRefInfoRepo.RateInfo">
      <compiled>true</compiled>
      <nonFcnCallPartitionName>D1</nonFcnCallPartitionName>
      <period>.001</period>
      <priority>40</priority>
      <rateIdx>0</rateIdx>
    </runtimeNonFcnCallRateInfos>
    <runtimeNonFcnCallRateInfos type="ModelRefInfoRepo.RateInfo">
      <compiled>true</compiled>
      <nonFcnCallPartitionName>D1</nonFcnCallPartitionName>
      <period>.01</period>
      <priority>40</priority>
      <rateIdx>1</rateIdx>
    </runtimeNonFcnCallRateInfos>
    <runtimeNonFcnCallRateInfos type="ModelRefInfoRepo.RateInfo">
      <compiled>true</compiled>
      <nonFcnCallPartitionName>D1</nonFcnCallPartitionName>
      <period>.5</period>
      <priority>40</priority>
      <rateIdx>2</rateIdx>
    </runtimeNonFcnCallRateInfos>
    <runtimeNonFcnCallRateInfos type="ModelRefInfoRepo.RateInfo">
      <compiled>true</compiled>
      <nonFcnCallPartitionName>D1</nonFcnCallPartitionName>
      <period>1.0</period>
      <priority>40</priority>
      <rateIdx>3</rateIdx>
    </runtimeNonFcnCallRateInfos>
    <runtimeNonFcnCallRateInfos type="ModelRefInfoRepo.RateInfo">
      <compiled>true</compiled>
      <nonFcnCallPartitionName>D1</nonFcnCallPartitionName>
      <period>100.0</period>
      <priority>40</priority>
      <rateIdx>4</rateIdx>
    </runtimeNonFcnCallRateInfos>
    <runtimeNonFcnCallRateInfos type="ModelRefInfoRepo.RateInfo">
      <compiled>true</compiled>
      <nonFcnCallPartitionName>D1</nonFcnCallPartitionName>
      <period>10000.0</period>
      <priority>40</priority>
      <rateIdx>5</rateIdx>
    </runtimeNonFcnCallRateInfos>
    <sampleTimeInheritanceRule>2</sampleTimeInheritanceRule>
    <solverStatusFlags>323</solverStatusFlags>
    <timingAndTaskingRegistry>&lt;?xml version=&quot;1.0&quot;?&gt;
&lt;slexec_sto version=&quot;1.1&quot; packageUris=&quot;http://schema.mathworks.com/mf0/slexec_mm_sto/R2023a_202208151321&quot;&gt;
  &lt;sto.Registry type=&quot;sto.Registry&quot; uuid=&quot;d3543d10-b207-4f76-a55c-80489bc4bf34&quot;&gt;
    &lt;executionSpec&gt;Undetermined&lt;/executionSpec&gt;
    &lt;identifier&gt;controller&lt;/identifier&gt;
    &lt;clockRegistry type=&quot;sto.ClockRegistry&quot; uuid=&quot;05c7217b-f7e5-49f3-9f21-d45e6811db1b&quot;&gt;
      &lt;clocks type=&quot;sto.Timer&quot; uuid=&quot;578af247-c119-437f-bc96-8dbd9f23546f&quot;&gt;
        &lt;clockTickConstraint&gt;PeriodicWithFixedResolution&lt;/clockTickConstraint&gt;
        &lt;computedFundamentalDiscretePeriod&gt;.001&lt;/computedFundamentalDiscretePeriod&gt;
        &lt;fastestDiscreteRate type=&quot;sto.ClassicPeriodicDiscreteRate&quot; uuid=&quot;af732c15-b193-4742-8681-4d08be1841a9&quot;/&gt;
        &lt;isDefaultTimer&gt;true&lt;/isDefaultTimer&gt;
        &lt;resolution&gt;.001&lt;/resolution&gt;
        &lt;timeAdvanceMode&gt;FixedStep&lt;/timeAdvanceMode&gt;
        &lt;identifier&gt;controller::defaultTimer&lt;/identifier&gt;
        &lt;rates type=&quot;sto.ClassicPeriodicDiscreteRate&quot; uuid=&quot;af732c15-b193-4742-8681-4d08be1841a9&quot;&gt;
          &lt;annotation&gt;D1&lt;/annotation&gt;
          &lt;clockId&gt;controller::defaultTimer&lt;/clockId&gt;
          &lt;description&gt;Discrete 1&lt;/description&gt;
          &lt;taskId&gt;_task0&lt;/taskId&gt;
          &lt;rateSpec type=&quot;sto.RateSpec&quot; uuid=&quot;d8e64795-a047-4d03-ac0e-a14f2fe3300b&quot;&gt;
            &lt;period&gt;.001&lt;/period&gt;
            &lt;rateType&gt;ClassicPeriodicDiscrete&lt;/rateType&gt;
          &lt;/rateSpec&gt;
        &lt;/rates&gt;
        &lt;rates type=&quot;sto.ClassicPeriodicDiscreteRate&quot; uuid=&quot;422a321d-9725-41eb-b2fd-61745b34c41c&quot;&gt;
          &lt;annotation&gt;D2&lt;/annotation&gt;
          &lt;clockId&gt;controller::defaultTimer&lt;/clockId&gt;
          &lt;colorIndex&gt;1&lt;/colorIndex&gt;
          &lt;description&gt;Discrete 2&lt;/description&gt;
          &lt;rateIdx&gt;1&lt;/rateIdx&gt;
          &lt;taskId&gt;_task0&lt;/taskId&gt;
          &lt;rateSpec type=&quot;sto.RateSpec&quot; uuid=&quot;97fccf59-0856-43ef-a504-92b5112e406b&quot;&gt;
            &lt;period&gt;.01&lt;/period&gt;
            &lt;rateType&gt;ClassicPeriodicDiscrete&lt;/rateType&gt;
          &lt;/rateSpec&gt;
        &lt;/rates&gt;
        &lt;rates type=&quot;sto.ClassicPeriodicDiscreteRate&quot; uuid=&quot;589de6bb-9748-45c7-bb54-6d77024b79b2&quot;&gt;
          &lt;annotation&gt;D3&lt;/annotation&gt;
          &lt;clockId&gt;controller::defaultTimer&lt;/clockId&gt;
          &lt;colorIndex&gt;2&lt;/colorIndex&gt;
          &lt;description&gt;Discrete 3&lt;/description&gt;
          &lt;rateIdx&gt;2&lt;/rateIdx&gt;
          &lt;taskId&gt;_task0&lt;/taskId&gt;
          &lt;rateSpec type=&quot;sto.RateSpec&quot; uuid=&quot;9fe40dab-4efe-46e2-a782-a1caf0b1cdac&quot;&gt;
            &lt;period&gt;.5&lt;/period&gt;
            &lt;rateType&gt;ClassicPeriodicDiscrete&lt;/rateType&gt;
          &lt;/rateSpec&gt;
        &lt;/rates&gt;
        &lt;rates type=&quot;sto.ClassicPeriodicDiscreteRate&quot; uuid=&quot;0971f402-cf06-400e-ba99-019f0f4fe299&quot;&gt;
          &lt;annotation&gt;D4&lt;/annotation&gt;
          &lt;clockId&gt;controller::defaultTimer&lt;/clockId&gt;
          &lt;colorIndex&gt;3&lt;/colorIndex&gt;
          &lt;description&gt;Discrete 4&lt;/description&gt;
          &lt;rateIdx&gt;3&lt;/rateIdx&gt;
          &lt;taskId&gt;_task0&lt;/taskId&gt;
          &lt;rateSpec type=&quot;sto.RateSpec&quot; uuid=&quot;edb2b47d-af64-477d-a58f-9254c4685a16&quot;&gt;
            &lt;period&gt;1.0&lt;/period&gt;
            &lt;rateType&gt;ClassicPeriodicDiscrete&lt;/rateType&gt;
          &lt;/rateSpec&gt;
        &lt;/rates&gt;
        &lt;rates type=&quot;sto.ClassicPeriodicDiscreteRate&quot; uuid=&quot;de522b68-a03c-4548-9df8-b2ca6e8a42c9&quot;&gt;
          &lt;annotation&gt;D5&lt;/annotation&gt;
          &lt;clockId&gt;controller::defaultTimer&lt;/clockId&gt;
          &lt;colorIndex&gt;4&lt;/colorIndex&gt;
          &lt;description&gt;Discrete 5&lt;/description&gt;
          &lt;rateIdx&gt;4&lt;/rateIdx&gt;
          &lt;taskId&gt;_task0&lt;/taskId&gt;
          &lt;rateSpec type=&quot;sto.RateSpec&quot; uuid=&quot;4c41f7bc-b26c-4932-9540-645d6c657289&quot;&gt;
            &lt;period&gt;100.0&lt;/period&gt;
            &lt;rateType&gt;ClassicPeriodicDiscrete&lt;/rateType&gt;
          &lt;/rateSpec&gt;
        &lt;/rates&gt;
        &lt;rates type=&quot;sto.ClassicPeriodicDiscreteRate&quot; uuid=&quot;dd20aac6-a27f-4172-af48-d8fc1fd89eca&quot;&gt;
          &lt;annotation&gt;D6&lt;/annotation&gt;
          &lt;clockId&gt;controller::defaultTimer&lt;/clockId&gt;
          &lt;colorIndex&gt;5&lt;/colorIndex&gt;
          &lt;description&gt;Discrete 6&lt;/description&gt;
          &lt;rateIdx&gt;5&lt;/rateIdx&gt;
          &lt;taskId&gt;_task0&lt;/taskId&gt;
          &lt;rateSpec type=&quot;sto.RateSpec&quot; uuid=&quot;4b760e56-fdc1-4662-a9b8-9053fdc821d5&quot;&gt;
            &lt;period&gt;10000.0&lt;/period&gt;
            &lt;rateType&gt;ClassicPeriodicDiscrete&lt;/rateType&gt;
          &lt;/rateSpec&gt;
        &lt;/rates&gt;
        &lt;baseRate type=&quot;sto.ClassicPeriodicDiscreteRate&quot; uuid=&quot;33f91815-98f9-42e2-9579-80396d370962&quot;&gt;
          &lt;annotation&gt;D1&lt;/annotation&gt;
          &lt;clockId&gt;controller::defaultTimer&lt;/clockId&gt;
          &lt;description&gt;Discrete 1&lt;/description&gt;
          &lt;taskId&gt;_task0&lt;/taskId&gt;
          &lt;rateSpec type=&quot;sto.RateSpec&quot; uuid=&quot;51433c6d-e439-41b2-bca1-8a9305d20e89&quot;&gt;
            &lt;period&gt;.001&lt;/period&gt;
            &lt;rateType&gt;ClassicPeriodicDiscrete&lt;/rateType&gt;
          &lt;/rateSpec&gt;
        &lt;/baseRate&gt;
      &lt;/clocks&gt;
      &lt;clocks type=&quot;sto.Event&quot; uuid=&quot;b6762d24-b9a1-41b6-80ec-dad8dab4289b&quot;&gt;
        &lt;eventType&gt;PARAMETER_CHANGE_EVENT&lt;/eventType&gt;
        &lt;cNum&gt;1&lt;/cNum&gt;
        &lt;clockType&gt;Event&lt;/clockType&gt;
        &lt;identifier&gt;ParameterChangeEvent&lt;/identifier&gt;
        &lt;rates type=&quot;sto.ModelWideEventRate&quot; uuid=&quot;5fb11d77-8061-41f7-ad52-e9c3409cb78e&quot;&gt;
          &lt;annotation&gt;Inf&lt;/annotation&gt;
          &lt;clockId&gt;ParameterChangeEvent&lt;/clockId&gt;
          &lt;colorIndex&gt;-1&lt;/colorIndex&gt;
          &lt;description&gt;Constant&lt;/description&gt;
          &lt;rateIdx&gt;-1&lt;/rateIdx&gt;
          &lt;taskId&gt;ModelWideParameterChangeEvent&lt;/taskId&gt;
          &lt;useForExecution&gt;NotForExecution&lt;/useForExecution&gt;
          &lt;rateSpec type=&quot;sto.RateSpec&quot; uuid=&quot;2baad3ec-f318-4109-9ce3-f82024bdf78e&quot;&gt;
            &lt;period&gt;inf&lt;/period&gt;
            &lt;rateType&gt;ModelWideParameterChangeEvent&lt;/rateType&gt;
          &lt;/rateSpec&gt;
        &lt;/rates&gt;
      &lt;/clocks&gt;
      &lt;timeAdvanceMode&gt;FixedStep&lt;/timeAdvanceMode&gt;
    &lt;/clockRegistry&gt;
    &lt;taskRegistry type=&quot;sto.TaskRegistry&quot; uuid=&quot;a354dd25-5b06-4a0c-a814-15223fad07bc&quot;&gt;
      &lt;rootTaskHierarchyElements type=&quot;sto.Task&quot; uuid=&quot;3bea70f8-8580-4bbf-ad7d-d62e6c8df13a&quot;&gt;
        &lt;isExplicit&gt;true&lt;/isExplicit&gt;
        &lt;rates type=&quot;sto.ModelWideEventRate&quot; uuid=&quot;00644a58-513a-4595-93df-f15b64ce8845&quot;&gt;
          &lt;annotation&gt;Inf&lt;/annotation&gt;
          &lt;clockId&gt;ParameterChangeEvent&lt;/clockId&gt;
          &lt;colorIndex&gt;-1&lt;/colorIndex&gt;
          &lt;description&gt;Constant&lt;/description&gt;
          &lt;rateIdx&gt;-1&lt;/rateIdx&gt;
          &lt;taskId&gt;ModelWideParameterChangeEvent&lt;/taskId&gt;
          &lt;useForExecution&gt;NotForExecution&lt;/useForExecution&gt;
          &lt;rateSpec type=&quot;sto.RateSpec&quot; uuid=&quot;183f1dde-9fa8-4836-aca7-483dd2f75d0d&quot;&gt;
            &lt;period&gt;inf&lt;/period&gt;
            &lt;rateType&gt;ModelWideParameterChangeEvent&lt;/rateType&gt;
          &lt;/rateSpec&gt;
        &lt;/rates&gt;
        &lt;schedulingClockId&gt;ParameterChangeEvent&lt;/schedulingClockId&gt;
        &lt;timeKeeperClockId&gt;controller::defaultTimer&lt;/timeKeeperClockId&gt;
        &lt;elementType&gt;Task&lt;/elementType&gt;
        &lt;identifier&gt;ModelWideParameterChangeEvent&lt;/identifier&gt;
        &lt;priority&gt;-1&lt;/priority&gt;
      &lt;/rootTaskHierarchyElements&gt;
      &lt;rootTaskHierarchyElements type=&quot;sto.Task&quot; uuid=&quot;e94ce147-b244-4c6b-876a-cbc6e42bccc6&quot;&gt;
        &lt;isExecutable&gt;true&lt;/isExecutable&gt;
        &lt;orderIndex&gt;1&lt;/orderIndex&gt;
        &lt;rates type=&quot;sto.ClassicPeriodicDiscreteRate&quot; uuid=&quot;d9469ac2-99bb-4835-840d-7ad6aedd278c&quot;&gt;
          &lt;annotation&gt;D1&lt;/annotation&gt;
          &lt;clockId&gt;controller::defaultTimer&lt;/clockId&gt;
          &lt;description&gt;Discrete 1&lt;/description&gt;
          &lt;taskId&gt;_task0&lt;/taskId&gt;
          &lt;rateSpec type=&quot;sto.RateSpec&quot; uuid=&quot;2bab1e3c-94b4-40dc-a08e-25610de25700&quot;&gt;
            &lt;period&gt;.001&lt;/period&gt;
            &lt;rateType&gt;ClassicPeriodicDiscrete&lt;/rateType&gt;
          &lt;/rateSpec&gt;
        &lt;/rates&gt;
        &lt;rates type=&quot;sto.ClassicPeriodicDiscreteRate&quot; uuid=&quot;7e318e5a-7343-439f-bcf3-779aee5bea36&quot;&gt;
          &lt;annotation&gt;D2&lt;/annotation&gt;
          &lt;clockId&gt;controller::defaultTimer&lt;/clockId&gt;
          &lt;colorIndex&gt;1&lt;/colorIndex&gt;
          &lt;description&gt;Discrete 2&lt;/description&gt;
          &lt;rateIdx&gt;1&lt;/rateIdx&gt;
          &lt;taskId&gt;_task0&lt;/taskId&gt;
          &lt;rateSpec type=&quot;sto.RateSpec&quot; uuid=&quot;035d3efb-3b15-4815-a0a6-981261315f22&quot;&gt;
            &lt;period&gt;.01&lt;/period&gt;
            &lt;rateType&gt;ClassicPeriodicDiscrete&lt;/rateType&gt;
          &lt;/rateSpec&gt;
        &lt;/rates&gt;
        &lt;rates type=&quot;sto.ClassicPeriodicDiscreteRate&quot; uuid=&quot;a663b472-43fd-4241-8956-514473a4823a&quot;&gt;
          &lt;annotation&gt;D3&lt;/annotation&gt;
          &lt;clockId&gt;controller::defaultTimer&lt;/clockId&gt;
          &lt;colorIndex&gt;2&lt;/colorIndex&gt;
          &lt;description&gt;Discrete 3&lt;/description&gt;
          &lt;rateIdx&gt;2&lt;/rateIdx&gt;
          &lt;taskId&gt;_task0&lt;/taskId&gt;
          &lt;rateSpec type=&quot;sto.RateSpec&quot; uuid=&quot;2a4775d0-de6c-40ba-8588-631293305a4a&quot;&gt;
            &lt;period&gt;.5&lt;/period&gt;
            &lt;rateType&gt;ClassicPeriodicDiscrete&lt;/rateType&gt;
          &lt;/rateSpec&gt;
        &lt;/rates&gt;
        &lt;rates type=&quot;sto.ClassicPeriodicDiscreteRate&quot; uuid=&quot;a191b174-3c9c-4a32-80a2-d20a42ba39f3&quot;&gt;
          &lt;annotation&gt;D4&lt;/annotation&gt;
          &lt;clockId&gt;controller::defaultTimer&lt;/clockId&gt;
          &lt;colorIndex&gt;3&lt;/colorIndex&gt;
          &lt;description&gt;Discrete 4&lt;/description&gt;
          &lt;rateIdx&gt;3&lt;/rateIdx&gt;
          &lt;taskId&gt;_task0&lt;/taskId&gt;
          &lt;rateSpec type=&quot;sto.RateSpec&quot; uuid=&quot;a9426732-7d73-40fd-ac8a-97bb968aaad2&quot;&gt;
            &lt;period&gt;1.0&lt;/period&gt;
            &lt;rateType&gt;ClassicPeriodicDiscrete&lt;/rateType&gt;
          &lt;/rateSpec&gt;
        &lt;/rates&gt;
        &lt;rates type=&quot;sto.ClassicPeriodicDiscreteRate&quot; uuid=&quot;49d094f6-1531-4dc5-b76b-8aebd1fab403&quot;&gt;
          &lt;annotation&gt;D5&lt;/annotation&gt;
          &lt;clockId&gt;controller::defaultTimer&lt;/clockId&gt;
          &lt;colorIndex&gt;4&lt;/colorIndex&gt;
          &lt;description&gt;Discrete 5&lt;/description&gt;
          &lt;rateIdx&gt;4&lt;/rateIdx&gt;
          &lt;taskId&gt;_task0&lt;/taskId&gt;
          &lt;rateSpec type=&quot;sto.RateSpec&quot; uuid=&quot;949d0441-e534-47b6-b942-37a826c68166&quot;&gt;
            &lt;period&gt;100.0&lt;/period&gt;
            &lt;rateType&gt;ClassicPeriodicDiscrete&lt;/rateType&gt;
          &lt;/rateSpec&gt;
        &lt;/rates&gt;
        &lt;rates type=&quot;sto.ClassicPeriodicDiscreteRate&quot; uuid=&quot;a7f6d3c3-65da-4b0e-b118-4f4af4845ae0&quot;&gt;
          &lt;annotation&gt;D6&lt;/annotation&gt;
          &lt;clockId&gt;controller::defaultTimer&lt;/clockId&gt;
          &lt;colorIndex&gt;5&lt;/colorIndex&gt;
          &lt;description&gt;Discrete 6&lt;/description&gt;
          &lt;rateIdx&gt;5&lt;/rateIdx&gt;
          &lt;taskId&gt;_task0&lt;/taskId&gt;
          &lt;rateSpec type=&quot;sto.RateSpec&quot; uuid=&quot;971589f6-a93a-43a3-8ac4-492243608eec&quot;&gt;
            &lt;period&gt;10000.0&lt;/period&gt;
            &lt;rateType&gt;ClassicPeriodicDiscrete&lt;/rateType&gt;
          &lt;/rateSpec&gt;
        &lt;/rates&gt;
        &lt;schedulingClockId&gt;controller::defaultTimer&lt;/schedulingClockId&gt;
        &lt;timeKeeperClockId&gt;controller::defaultTimer&lt;/timeKeeperClockId&gt;
        &lt;elementType&gt;Task&lt;/elementType&gt;
        &lt;identifier&gt;_task0&lt;/identifier&gt;
        &lt;priority&gt;40&lt;/priority&gt;
      &lt;/rootTaskHierarchyElements&gt;
      &lt;taskDependencyGraph type=&quot;sto.SerializedTaskConnectionList&quot; uuid=&quot;16150845-e0ad-4346-abfc-f2ce1caedfb0&quot;&gt;
        &lt;clockIdentifier&gt;controller::defaultTimer&lt;/clockIdentifier&gt;
        &lt;taskIdentifier&gt;_task0&lt;/taskIdentifier&gt;
      &lt;/taskDependencyGraph&gt;
      &lt;taskDependencyGraph type=&quot;sto.SerializedTaskConnectionList&quot; uuid=&quot;8dbce113-c741-4ce8-a162-eded8b0caf26&quot;&gt;
        &lt;clockIdentifier&gt;ParameterChangeEvent&lt;/clockIdentifier&gt;
        &lt;taskIdentifier&gt;ModelWideParameterChangeEvent&lt;/taskIdentifier&gt;
      &lt;/taskDependencyGraph&gt;
    &lt;/taskRegistry&gt;
  &lt;/sto.Registry&gt;
&lt;/slexec_sto&gt;</timingAndTaskingRegistry>
    <zeroCrossingInfo type="ModelRefInfoRepo.ZeroCrossingInfo" uuid="4dd9ea83-a46d-4fd7-bee6-f8dbac901893">
      <direction>7</direction>
      <isDiscrete>true</isDiscrete>
      <name>Trig</name>
      <needsEventNotification>true</needsEventNotification>
      <tolerance>-1.0</tolerance>
      <type>1</type>
      <width>1</width>
    </zeroCrossingInfo>
    <zeroCrossingInfo type="ModelRefInfoRepo.ZeroCrossingInfo" uuid="d9a114bc-b04e-4064-a8fd-57ee4c92db77">
      <direction>7</direction>
      <isDiscrete>true</isDiscrete>
      <name>Trig</name>
      <needsEventNotification>true</needsEventNotification>
      <tolerance>-1.0</tolerance>
      <type>1</type>
      <width>1</width>
    </zeroCrossingInfo>
    <zeroCrossingInfo type="ModelRefInfoRepo.ZeroCrossingInfo" uuid="4d2c284b-5bdf-459b-856d-d718a23c1f81">
      <direction>7</direction>
      <isDiscrete>true</isDiscrete>
      <name>Trig</name>
      <needsEventNotification>true</needsEventNotification>
      <tolerance>-1.0</tolerance>
      <type>1</type>
      <width>1</width>
    </zeroCrossingInfo>
    <FMUBlockMap type="ModelRefInfoRepo.FMUBlockInfo" uuid="60510bce-35c6-4034-aa8b-4d404bf31a4f"/>
    <codeGenInfo type="ModelRefInfoRepo.CodeGenInformation" uuid="213196ae-be26-479c-997f-811dba4ab1b0"/>
    <compiledVariantInfos type="ModelRefInfoRepo.CompiledVariantInfoMap" uuid="a5353908-4c70-4b57-804f-683a0fb3a421"/>
    <configSettingsForConsistencyChecks type="ModelRefInfoRepo.ConfigSettingsForConsistencyChecks" uuid="bf0791ca-ac58-4a26-9542-1c08b782e32b">
      <consistentOutportInitialization>true</consistentOutportInitialization>
      <fixedStepSize>.001</fixedStepSize>
      <frameDiagnosticSetting>2</frameDiagnosticSetting>
      <hasHybridSampleTime>true</hasHybridSampleTime>
      <signalLoggingSaveFormat>2</signalLoggingSaveFormat>
      <simSIMDOptimization>1</simSIMDOptimization>
      <solverName>FixedStepDiscrete</solverName>
      <solverType>SOLVER_TYPE_FIXEDSTEP</solverType>
      <hardwareSettings type="ModelRefInfoRepo.HardwareSettings" uuid="66894047-ade3-4cb9-9d6e-e29cdbd2dce1">
        <prodBitPerChar>8</prodBitPerChar>
        <prodBitPerDouble>64</prodBitPerDouble>
        <prodBitPerFloat>32</prodBitPerFloat>
        <prodBitPerInt>32</prodBitPerInt>
        <prodBitPerLong>32</prodBitPerLong>
        <prodBitPerLongLong>64</prodBitPerLongLong>
        <prodBitPerPointer>32</prodBitPerPointer>
        <prodBitPerPtrDiffT>32</prodBitPerPtrDiffT>
        <prodBitPerShort>16</prodBitPerShort>
        <prodBitPerSizeT>32</prodBitPerSizeT>
        <prodEndianess>1</prodEndianess>
        <prodLargestAtomicFloat>1</prodLargestAtomicFloat>
        <prodLargestAtomicInteger>3</prodLargestAtomicInteger>
        <prodShiftRight>true</prodShiftRight>
        <prodWordSize>32</prodWordSize>
      </hardwareSettings>
    </configSettingsForConsistencyChecks>
    <controllableInputRatesMap type="ModelRefInfoRepo.VarTsUIDMap" uuid="2b325018-d1b8-4292-929f-923334e0701a"/>
    <controllableOutputRatesMap type="ModelRefInfoRepo.VarTsUIDMap" uuid="1181ef9f-9ccd-462d-ac3f-c5aae58d6eb2"/>
    <dataPortGroup type="ModelRefInfoRepo.DataPortGroup" uuid="420a59c6-358a-4d12-9f4b-a890ba277b41"/>
    <expFcnUnconnectedDataPortGroup type="ModelRefInfoRepo.DataPortGroup" uuid="ac57a885-d890-4719-b7e0-055cc4ea6439"/>
    <interfaceParameterInfo type="ModelRefInfoRepo.InterfaceParameterInfo" uuid="8f2e5a07-4f61-4a31-8201-8a08808cea84"/>
    <messageInfo type="ModelRefInfoRepo.MessageInformation" uuid="ba1b25cf-a773-4103-806f-0fc5d6bce168"/>
    <methodInfo type="ModelRefInfoRepo.MethodExistenceInfo" uuid="b3f1c5f2-fe7a-471a-957e-39f2501496b2">
      <hasDisableMethod>true</hasDisableMethod>
      <hasEnableMethod>true</hasEnableMethod>
      <hasSystemInitializeMethod>true</hasSystemInitializeMethod>
      <hasSystemResetMethod>true</hasSystemResetMethod>
      <hasTerminateMethod>true</hasTerminateMethod>
      <hasUpdateMethod>true</hasUpdateMethod>
    </methodInfo>
    <periodicEventPortUnsupportedBlockInfo type="ModelRefInfoRepo.PeriodicEventPortUnsupportedBlockInfo" uuid="9e71c4ea-e20b-402e-9a42-ac64fb7b9410">
      <multiRateSubsystems>controller/Home1</multiRateSubsystems>
      <multiRateSubsystems>controller/Initialize</multiRateSubsystems>
      <multiRateSubsystems>controller/Main Control</multiRateSubsystems>
    </periodicEventPortUnsupportedBlockInfo>
    <portGroupsRequireSameRate type="ModelRefInfoRepo.PortGroupsRequireSameRate" uuid="c8bf3234-32a0-4a9d-9d85-cfd5ca7193a4">
      <DSMPortGroups type="ModelRefInfoRepo.NameToPortGroupIdxVectMap" uuid="e1ebc7cb-206d-465a-9424-d14e62c16f06"/>
      <GlobalDSMPortGroups type="ModelRefInfoRepo.NameToPortGroupIdxVectMap" uuid="0536b3c7-0108-4028-ae4f-96d1092e1004"/>
      <mergedPortGroups type="ModelRefInfoRepo.NameToPortGroupIdxVectMap" uuid="5210fd25-5184-4544-a7da-f3bb8d8f5693"/>
    </portGroupsRequireSameRate>
    <rateBasedMdlGlobalDSMRateSpec type="ModelRefInfoRepo.GlobalDSMRateSpecMap" uuid="e255bbd9-7394-4222-bfb3-79f563ce66cf"/>
    <rateSpecOfGlobalDSMAccessedByDescExpFcnMdlMap type="ModelRefInfoRepo.GlobalDSMRateSpecMap" uuid="64135795-f8e4-43cf-b5b7-05eb62306893"/>
    <rootBlockDiagramInterface type="ci.Model" uuid="00ea2dfa-2c7a-42c0-a748-19548315a951">
      <p_RootComponentInterface type="ci.ComponentInterface" uuid="81fa4ee2-a26e-4698-90bb-756ded5d2c3d">
        <p_Name>controller</p_Name>
        <p_Type>ROOT</p_Type>
      </p_RootComponentInterface>
    </rootBlockDiagramInterface>
    <simulinkFunctions type="ModelRefInfoRepo.SimulinkFunctions" uuid="b910f948-b600-4ceb-8355-437fb30565a2">
      <compSimulinkFunctionCatalog></compSimulinkFunctionCatalog>
    </simulinkFunctions>
    <sltpContext type="sltp.mm.core.Context" uuid="d1ee3b34-9c0e-4450-8936-d07ee0e1718c">
      <globalData type="sltp.mm.core.GlobalData" uuid="a1376d38-b926-4f9f-9a6e-4ac1d4097aee">
        <dataName>portOut1</dataName>
        <type>RootOutport</type>
      </globalData>
      <unusedTaskIds>1</unusedTaskIds>
      <defaultEventBehavior type="sltp.mm.core.EventBehavior" uuid="c8550307-0065-4968-b024-64ca45bc0eb5"/>
      <editorState type="sltp.mm.core.EditorState" uuid="3429ef35-ff8f-40e9-9e53-88ef0319603d">
        <isSynchronized>true</isSynchronized>
        <panelState type="sltp.mm.core.EditorPanelState" uuid="4d0a93cc-e9a0-4489-8f2d-c729ee71b0ac"/>
      </editorState>
      <rootTask type="sltp.mm.core.Task" uuid="5d27843a-d651-421f-9166-f7c9adc22d38">
        <context type="sltp.mm.core.Context" uuid="d1ee3b34-9c0e-4450-8936-d07ee0e1718c"/>
        <explicit>false</explicit>
        <name>Default</name>
        <priority>-2147483648</priority>
        <subgraph type="sltp.mm.core.Graph" uuid="f6fd6b47-38c2-4d95-ae0c-85e031d5b592">
          <tasks type="sltp.mm.core.Task" uuid="f5dfb715-85bb-4f7a-9b19-b94f22b5ed6c">
            <context type="sltp.mm.core.Context" uuid="d1ee3b34-9c0e-4450-8936-d07ee0e1718c"/>
            <explicit>false</explicit>
            <id>2</id>
            <isTimed>true</isTimed>
            <name>D1</name>
            <priority>40</priority>
            <rates type="sltp.mm.core.Rate" uuid="e69eb1e9-6a91-4cf7-bbfe-e1c533bae615">
              <annotation>D1</annotation>
              <color>-12240129</color>
              <hasBlocks>true</hasBlocks>
              <identifier>ClassicPeriodicDiscrete0.0010</identifier>
              <rateIndex>0</rateIndex>
              <rateSpec type="sltp.mm.core.RateSpec">
                <period>.001</period>
              </rateSpec>
              <sti>0</sti>
            </rates>
            <rates type="sltp.mm.core.Rate" uuid="20293fbe-3f92-4465-8471-0383cce7d43c">
              <annotation>D2</annotation>
              <color>986198527</color>
              <hasBlocks>true</hasBlocks>
              <rateIndex>1</rateIndex>
              <rateSpec type="sltp.mm.core.RateSpec">
                <period>.01</period>
              </rateSpec>
              <sti>1</sti>
            </rates>
            <rates type="sltp.mm.core.Rate" uuid="5fca017d-99c0-4cd0-b532-5f7a48a11008">
              <annotation>D3</annotation>
              <color>234946559</color>
              <hasBlocks>true</hasBlocks>
              <rateIndex>2</rateIndex>
              <rateSpec type="sltp.mm.core.RateSpec">
                <period>.5</period>
              </rateSpec>
              <sti>2</sti>
            </rates>
            <rates type="sltp.mm.core.Rate" uuid="85696709-e080-481f-9eb2-a3ab7145f4b9">
              <annotation>D4</annotation>
              <color>234946559</color>
              <hasBlocks>true</hasBlocks>
              <rateIndex>3</rateIndex>
              <rateSpec type="sltp.mm.core.RateSpec">
                <period>1.0</period>
              </rateSpec>
              <sti>3</sti>
            </rates>
            <rates type="sltp.mm.core.Rate" uuid="c66106ef-c370-4876-ae1d-0d04d3d255c2">
              <annotation>D5</annotation>
              <color>234946559</color>
              <hasBlocks>true</hasBlocks>
              <rateIndex>4</rateIndex>
              <rateSpec type="sltp.mm.core.RateSpec">
                <period>100.0</period>
              </rateSpec>
              <sti>4</sti>
            </rates>
            <rates type="sltp.mm.core.Rate" uuid="71a8a795-7176-4ed2-b45f-7b7916e4a203">
              <annotation>D6</annotation>
              <color>234946559</color>
              <hasBlocks>true</hasBlocks>
              <rateIndex>5</rateIndex>
              <rateSpec type="sltp.mm.core.RateSpec">
                <period>10000.0</period>
              </rateSpec>
              <sti>5</sti>
            </rates>
          </tasks>
        </subgraph>
      </rootTask>
    </sltpContext>
    <stateWriterToOwnerMap type="ModelRefInfoRepo.StateWriterInfo" uuid="f6eca19d-7dc1-4430-b71a-39f4e695dbab"/>
    <stoClientDataRegistry type="sto.ClientDataRegistry" uuid="cc40fb0d-f465-423d-b328-81fdd80eca7e">
      <dataSets type="sto.ClientClockNamedDataSet" uuid="99bac34f-83e4-4fa7-a216-f62100b179a7">
        <tag>sltpEvents</tag>
      </dataSets>
      <dataSets type="sto.ClientTaskHierarchyElementNamedDataSet" uuid="686a4033-1ed0-4ad5-a1da-6be6e045532d">
        <tag>sltpTaskGroups</tag>
      </dataSets>
      <dataSets type="sto.ClientTaskHierarchyElementNamedDataSet" uuid="13ffcdc9-da2d-4afd-8335-ab3879412265">
        <dSet type="ModelRefInfoRepo.SltpTaskData" uuid="98bd237f-687f-466b-93e7-32c0ce7d1301"/>
        <tSet type="ModelRefInfoRepo.SltpTaskData" uuid="98bd237f-687f-466b-93e7-32c0ce7d1301">
          <dataName>D1</dataName>
          <linkedSet type="sto.ClientTaskHierarchyElementNamedDataSet" uuid="13ffcdc9-da2d-4afd-8335-ab3879412265"/>
          <id type="sto.TaskHierarchyElementId">
            <clockId>controller::defaultTimer</clockId>
            <id>_task0</id>
          </id>
        </tSet>
        <tag>sltpTasks</tag>
      </dataSets>
    </stoClientDataRegistry>
    <varTsUIDMap type="ModelRefInfoRepo.VarTsUIDMap" uuid="cc0532dd-14b1-45ac-b5ba-0388abb6f874"/>
  </ModelRefInfoRepo.ModelRefInfoRoot>
</MF0>